datalib/__init__.py
datalib/utils.py
datalib/analysis/__init__.py
datalib/analysis/classification.py
datalib/analysis/clustering.py
datalib/analysis/regression.py
datalib/data/__init__.py
datalib/data/csv_handler.py
datalib/data/data_cleaning.py
datalib/stats/__init__.py
datalib/stats/descriptive_stats.py
datalib/stats/statistical_tests.py
datalib/visualization/__init__.py
datalib/visualization/advanced_plots.py
datalib/visualization/simple_plots.py
haithem_datalib-0.1.0.dist-info/LICENSE
haithem_datalib-0.1.0.dist-info/METADATA
haithem_datalib-0.1.0.dist-info/WHEEL
haithem_datalib-0.1.0.dist-info/top_level.txt
haithem_datalib-0.1.0.dist-info/RECORD
