Metadata-Version: 2.1
Name: haithem-datalib
Version: 0.1.0
Summary: A Python library for data manipulation and analysis
Home-page: https://github.com/HaithemBenSlama/haithem-dataLib
Author: Haithem Ben Slama
Author-email: haithem.benslama@hotmail.fr
License: MIT
Classifier: Programming Language :: Python :: 3
Classifier: License :: OSI Approved :: MIT License
Classifier: Operating System :: OS Independent
Classifier: Intended Audience :: Developers
Classifier: Topic :: Software Development :: Libraries :: Python Modules
Requires-Python: >=3.7
License-File: LICENSE
Requires-Dist: numpy>=1.21.0
Requires-Dist: pandas>=1.3.0
Requires-Dist: matplotlib>=3.4.0
Requires-Dist: scikit-learn>=0.24.0
